odoo/addons/mrp_bom_structure_xlsx_level_1/README.rst
odoo/addons/mrp_bom_structure_xlsx_level_1/__init__.py
odoo/addons/mrp_bom_structure_xlsx_level_1/__manifest__.py
odoo/addons/mrp_bom_structure_xlsx_level_1/i18n/de.po
odoo/addons/mrp_bom_structure_xlsx_level_1/i18n/it.po
odoo/addons/mrp_bom_structure_xlsx_level_1/i18n/mrp_bom_structure_xlsx_level_1.pot
odoo/addons/mrp_bom_structure_xlsx_level_1/readme/CONTRIBUTORS.rst
odoo/addons/mrp_bom_structure_xlsx_level_1/readme/DESCRIPTION.rst
odoo/addons/mrp_bom_structure_xlsx_level_1/readme/USAGE.rst
odoo/addons/mrp_bom_structure_xlsx_level_1/report/__init__.py
odoo/addons/mrp_bom_structure_xlsx_level_1/report/bom_structure_xlsx.py
odoo/addons/mrp_bom_structure_xlsx_level_1/report/bom_structure_xlsx.xml
odoo/addons/mrp_bom_structure_xlsx_level_1/static/description/icon.png
odoo/addons/mrp_bom_structure_xlsx_level_1/static/description/index.html
odoo12_addon_mrp_bom_structure_xlsx_level_1-12.0.1.0.0.99.dev8.dist-info/METADATA
odoo12_addon_mrp_bom_structure_xlsx_level_1-12.0.1.0.0.99.dev8.dist-info/WHEEL
odoo12_addon_mrp_bom_structure_xlsx_level_1-12.0.1.0.0.99.dev8.dist-info/top_level.txt
odoo12_addon_mrp_bom_structure_xlsx_level_1-12.0.1.0.0.99.dev8.dist-info/RECORD
