Metadata-Version: 2.1
Name: odoo12-addon-mrp-bom-structure-xlsx-level-1
Version: 12.0.1.0.0.99.dev8
Summary: Export BOM Structure (Level 1) to Excel .XLSX
Home-page: https://github.com/OCA/manufacture-reporting
Author: Eficent, Odoo Community Association (OCA)
Author-email: support@odoo-community.org
License: AGPL-3
Platform: UNKNOWN
Classifier: Programming Language :: Python
Classifier: Framework :: Odoo
Classifier: Framework :: Odoo :: 12.0
Classifier: License :: OSI Approved :: GNU Affero General Public License v3
Requires-Python: >=3.5
Requires-Dist: odoo12-addon-mrp-bom-structure-xlsx
Requires-Dist: odoo <12.1dev,>=12.0a
